{"_path":"/footer","_dir":"","_draft":false,"_partial":false,"_locale":"","navigation":"false","text":"Made by Lefteris Charteros","social":[{"name":"Github","url":"https://github.com/harteros","icon":"i-tabler-brand-github"},{"name":"Linkedin","url":"https://www.linkedin.com/in/lefteris-charteros/","icon":"i-tabler-brand-linkedin"},{"name":"Twitter","url":"https://x.com/lcharteros","icon":"i-tabler-brand-twitter"}],"_id":"content:footer.json","_type":"json","title":"Footer","_source":"content","_file":"footer.json","_stem":"footer","_extension":"json"}